aquacrop_abses/__init__.py
aquacrop_abses/_constants.py
aquacrop_abses/_types.py
aquacrop_abses/cell.py
aquacrop_abses/config/default.yaml
aquacrop_abses/config/ds/hym.yaml
aquacrop_abses/config/ds/ss.yaml
aquacrop_abses/config/farmer/irr_method_0.yaml
aquacrop_abses/config/farmer/irr_method_1.yaml
aquacrop_abses/config/farmer/irr_method_2.yaml
aquacrop_abses/config/farmer/irr_method_3.yaml
aquacrop_abses/config/farmer/irr_method_4.yaml
aquacrop_abses/config/farmer/irr_method_5.yaml
aquacrop_abses/config.py
aquacrop_abses/farmer.py
aquacrop_abses/load_datasets.py
aquacrop_abses/nature.py
aquacrop_abses-0.5.1.dist-info/METADATA
aquacrop_abses-0.5.1.dist-info/WHEEL
aquacrop_abses-0.5.1.dist-info/licenses/LICENSE
aquacrop_abses-0.5.1.dist-info/RECORD
