Metadata-Version: 2.4
Name: aquacrop-abses
Version: 0.5.1
Summary: 
License-File: LICENSE
Author: SongshGeo
Author-email: songshgeo@gmail.com
Requires-Python: >=3.11,<3.13
Classifier: Programming Language :: Python :: 3
Classifier: Programming Language :: Python :: 3.11
Classifier: Programming Language :: Python :: 3.12
Requires-Dist: abses (>=0.9.0)
Requires-Dist: aquacrop (>=3,<4)
Requires-Dist: matplotkit (>=0.1.2)
Requires-Dist: seaborn (>=0,<1)
